Metadata-Version: 1.0
Name: AMdistributions
Version: 0.1
Summary: Gaussian and Binomial distributions
Home-page: UNKNOWN
Author: Ali Mbacho
Author-email: UNKNOWN
License: UNKNOWN
Platform: UNKNOWN
